Metadata-Version: 2.1
Name: area-calculator-dci_mori_fazel
Version: 0.0.1
Summary: Calculate areas of geometrical figures
Author: Mori Fazel
Classifier: Programming Language :: Python :: 3
Classifier: License :: OSI Approved :: MIT License
Classifier: Operating System :: OS Independent
Requires-Python: >=3.6
License-File: LICENSE
